dummypackage12624/__init__.py
dummypackage12624/add.py
dummypackage12624/custom_exception.py
dummypackage12624/logger.py
dummypackage12624-0.0.40.dist-info/LICENSE
dummypackage12624-0.0.40.dist-info/METADATA
dummypackage12624-0.0.40.dist-info/WHEEL
dummypackage12624-0.0.40.dist-info/top_level.txt
dummypackage12624-0.0.40.dist-info/RECORD
