Metadata-Version: 2.1
Name: dummypackage12624
Version: 0.0.40
Summary: Dummy python package
Home-page: https://github.com/ronylpatil/test_package
Author: ronilpatil
Author-email: xyz@gmail.com
License: MIT
Project-URL: Source, https://github.com/ronylpatil/test_package
Project-URL: Bug Tracker, https://github.com/ronylpatil/test_package/issues
Project-URL: Changelog, https://github.com/ronylpatil/test_package/releases
Keywords: package,python,pytest
Classifier: Development Status :: 4 - Beta
Classifier: License :: OSI Approved :: MIT License
Classifier: Operating System :: MacOS
Classifier: Operating System :: Microsoft :: Windows
Classifier: Operating System :: POSIX :: Linux
Classifier: Environment :: Console
Classifier: Natural Language :: English
Classifier: Intended Audience :: Developers
Classifier: Intended Audience :: Science/Research
Classifier: Programming Language :: Python :: 3.9
Classifier: Programming Language :: Python :: 3.10
Classifier: Programming Language :: Python :: 3.11
Classifier: Programming Language :: Python :: 3.12
Classifier: Topic :: Communications :: Chat
Classifier: Topic :: Scientific/Engineering :: Information Analysis
Classifier: Topic :: Scientific/Engineering :: Visualization
Requires-Python: >=3.9
License-File: LICENSE
Requires-Dist: ensure ==1.0.2
Provides-Extra: testing
Requires-Dist: pytest >=8.2.2 ; extra == 'testing'
Requires-Dist: mypy >=1.10.0 ; extra == 'testing'
Requires-Dist: flake8 >=7.0.0 ; extra == 'testing'
Requires-Dist: tox >=4.15.1 ; extra == 'testing'
Requires-Dist: black >=24.4.2 ; extra == 'testing'
